{"HNitNGpKZi5fN+5K/JcaQA==":"popx-180x180.png","Cni5rubhf+SJutem21ZTGg==":"mbr-1440x1080.jpg","TGKqb1a3NKotOP8L4RoCfw==":"mbr-1620x1080.jpg","BZyqz7liy5X/HnfMEWV8iw==":"mbr-1-1620x1080.jpg","E0khmTTZdOHgNfBgkB/5Hg==":"mbr-2-1620x1080.jpg","swCeiUsvdKUf4BnZpxX0Xw==":"rockcontent-1100x250.png","68He6dojpiorANPmIW4n7g==":"b2bee-1200x468.png","uguExipmhFWwwSsrgn4SWw==":"rockcontent-branco-1100x250.png","r9BEEl/AOvj1RokNsMgFrg==":"b2bee-branco-1200x468.png","QnZWSKT8IHYI3doYMgcDpQ==":"logomeliuz-400x200.png","VaDKHs2EMVyux69tW9af+g==":"pipedrive-700x469.png","7UXO4aClHFvzV4KyH2VACA==":"pipefy-logo-white-blue-1-3650x1020.png","eQNgtp4vnmjBoOM31cEwMw==":"b2bee-small-256x100.png","h+pGNYMgREoMQiDFQ+R2MA==":"wplogo-120x100-12-120x100.png","BLVayFmcE0DugFEk6+IDCQ==":"logogoogle-120x100-23-120x100.png","+FMHE48WLS0mZNUA9nKzuw==":"footer-logo-microsoft-studios-120x100.png","GyYWd8PfW8WtDd2QfsPSuA==":"salesforce-w-600x420.png","j8j3pXVMXIhnELsD2X6kjw==":"xsenac-logo.pagespeed.ic.bl2nu8vmna-120x100.png-120x100.png","zh2/asNpJ1xv9b+8Gt5uIQ==":"hotmart-aplica%C3%A7%C3%A3o-horizontal-1024x449.png","L2BwD+ZC4SfeBshbU21idQ==":"logo-meliuz-940x399.png","6PBo2AdvFzyJWCYNqw5rnw==":"vulpi-logo-555x555.png","ZqJYuSlamNXGiVKlmxB5pw==":"hubspot-logo-500x187.png","q8NbeYMwYMHPP0do0AoRWA==":"maxmilhas-1280x366.png","guwGfu6EopBfdh4CGJeGqg==":"popsocial-2-282x207.png","nmHph7c2tcKGR/iHe9XnQQ==":"popsocial1-425x307.png","liiflUVQ+CGD8W1X4VjsGg==":"popsocial4-588x322.png","gtf7EVeEfiGlcfw5fsG28A==":"popsocial5-588x322.png","Th7JJzq3vxAt+zi22e4SFQ==":"group%20174-1092x540.png","qbO020c2TPAZ4axr88GfwA==":"gif.gif"}